MANIFEST.in
setup.py
runningz_automl/__init__.py
runningz_automl/runningz_automl.cpython-37m-x86_64-linux-gnu.so
runningz_automl.egg-info/PKG-INFO
runningz_automl.egg-info/SOURCES.txt
runningz_automl.egg-info/dependency_links.txt
runningz_automl.egg-info/not-zip-safe
runningz_automl.egg-info/top_level.txt