Metadata-Version: 1.0
Name: runningz-automl
Version: 0.0.2
Summary: runningz_automl
Home-page: https://github.com/RunxingZhong/stacking_automl_001
Author: zhongrunxinig
Author-email: zhongrunxing@gmail.com
License: MIT
Platform: UNKNOWN
